pyhcl_fancy/__init__.py
pyhcl_fancy/blocks/__init__.py
pyhcl_fancy/blocks/real/__init__.py
pyhcl_fancy/blocks/real/data/__init__.py
pyhcl_fancy/blocks/real/data/data_block.py
pyhcl_fancy/blocks/real/module/__init__.py
pyhcl_fancy/blocks/real/module/module_block.py
pyhcl_fancy/blocks/real/real_block.py
pyhcl_fancy/blocks/real/resource/__init__.py
pyhcl_fancy/blocks/real/resource/resource_block.py
pyhcl_fancy/blocks/reference/__init__.py
pyhcl_fancy/blocks/reference/local/__init__.py
pyhcl_fancy/blocks/reference/local/local_block.py
pyhcl_fancy/blocks/reference/meta/__init__.py
pyhcl_fancy/blocks/reference/meta/meta_block.py
pyhcl_fancy/blocks/reference/output/__init__.py
pyhcl_fancy/blocks/reference/output/output_block.py
pyhcl_fancy/blocks/reference/provider/__init__.py
pyhcl_fancy/blocks/reference/provider/provider_block.py
pyhcl_fancy/blocks/reference/variable/__init__.py
pyhcl_fancy/blocks/reference/variable/variable_block.py
pyhcl_fancy/blocks/terraform_block.py
pyhcl_fancy/collection_tree/__init__.py
pyhcl_fancy/collection_tree/exceptions.py
pyhcl_fancy/collection_tree/node.py
pyhcl_fancy/collection_tree/tree.py
pyhcl_fancy/parser/__init__.py
pyhcl_fancy/parser/exceptions.py
pyhcl_fancy/parser/parser.py
pyhcl_fancy/parser/utils.py
pyhcl_fancy-1.0.0.dist-info/LICENSE
pyhcl_fancy-1.0.0.dist-info/METADATA
pyhcl_fancy-1.0.0.dist-info/WHEEL
pyhcl_fancy-1.0.0.dist-info/RECORD
